dlc2yolo/__about__.py
dlc2yolo/__init__.py
dlc2yolo/dlc2yolo.py
dlc2yolo-1.0.0.dist-info/METADATA
dlc2yolo-1.0.0.dist-info/WHEEL
dlc2yolo-1.0.0.dist-info/top_level.txt
dlc2yolo-1.0.0.dist-info/RECORD
