Metadata-Version: 2.1
Name: dlc2yolo
Version: 1.0.0
Summary: Convert DeepLabCut dataset to YOLO format
Author-email: Hakureirm <wbj010101@gmail.com>
Project-URL: Homepage, https://github.com/Hakureirm/dlc2yolo
Project-URL: Repository, https://github.com/Hakureirm/dlc2yolo
Project-URL: Issues, https://github.com/Hakureirm/dlc2yolo/issues
Classifier: Programming Language :: Python :: 3
Classifier: License :: OSI Approved :: GNU General Public License v3 (GPLv3)
Classifier: Operating System :: OS Independent
Classifier: Topic :: Scientific/Engineering :: Artificial Intelligence
Requires-Python: >=3.8
Requires-Dist: pandas
